CGIRMS
